LICENSE
MANIFEST.in
README.rst
requirements.txt
setup.py
ctfile/__init__.py
ctfile/api.py
ctfile/coloring.py
ctfile/conf.py
ctfile/ctfile.py
ctfile/exceptions.py
ctfile/tokenizer.py
ctfile/utils.py
ctfile.egg-info/PKG-INFO
ctfile.egg-info/SOURCES.txt
ctfile.egg-info/dependency_links.txt
ctfile.egg-info/requires.txt
ctfile.egg-info/top_level.txt
ctfile/config_files/Charge_index.json
ctfile/config_files/Ctab_properties.json
ctfile/config_files/Index_charge.json