Metadata-Version: 1.1
Name: ctfile
Version: 0.1.12
Summary: Parser for chemical table file (CTfile) a family of text-based chemical file formats (e.g. Molfile, SDfile) that describe molecules and chemical reactions.
Home-page: https://github.com/MoseleyBioinformaticsLab/ctfile
Author: Andrey Smelter, Huan Jin
Author-email: andrey.smelter@gmail.com, jinhuan0905@gmail.com
License: BSD
Keywords: CTfile SDfile Molfile Ctab
Platform: any
Classifier: Development Status :: 4 - Beta
Classifier: Environment :: Console
Classifier: Intended Audience :: Developers
Classifier: Intended Audience :: Science/Research
Classifier: License :: OSI Approved :: BSD License
Classifier: Operating System :: OS Independent
Classifier: Programming Language :: Python :: 2.7
Classifier: Programming Language :: Python :: 3.4
Classifier: Programming Language :: Python :: 3.5
Classifier: Programming Language :: Python :: 3.6
Classifier: Programming Language :: Python :: 3.7
Classifier: Topic :: Scientific/Engineering :: Bio-Informatics
Classifier: Topic :: Software Development :: Libraries :: Python Modules
